autodyn/__init__.py
autodyn/analysis/__init__.py
autodyn/analysis/lieLib.py
autodyn/core/__init__.py
autodyn/core/dynamical.py
autodyn/core/integrators/__init__.py
autodyn/core/integrators/runge_kutta.py
autodyn/core/network.py
autodyn/models/__init__.py
autodyn/models/canonical/__init__.py
autodyn/models/canonical/standard.py
autodyn/models/drift_dynamics/__init__.py
autodyn/models/neuro/__init__.py
autodyn/models/neuro/wc.py
autodyn/utils/__init__.py
autodyn/utils/functions.py
autodyn/viz/__init__.py
autodyn/viz/anim_class.py
autodyn/viz/net_viz_lib.py
autodyn-0.1.5.dist-info/LICENSE
autodyn-0.1.5.dist-info/METADATA
autodyn-0.1.5.dist-info/WHEEL
autodyn-0.1.5.dist-info/RECORD
