Metadata-Version: 2.1
Name: autodyn
Version: 0.1.5
Summary: Differentiable Dynamical Systems
License: MIT
Author: Vineet Tiruvadi
Author-email: virati@gmail.com
Requires-Python: >=3.10,<4.0
Classifier: License :: OSI Approved :: MIT License
Classifier: Programming Language :: Python :: 3
Classifier: Programming Language :: Python :: 3.10
Classifier: Programming Language :: Python :: 3.11
Classifier: Programming Language :: Python :: 3.12
Requires-Dist: jax (>=0.4.25,<0.5.0)
Requires-Dist: matplotlib (>=3.8.3,<4.0.0)
Requires-Dist: networkx (>=3.2.1,<4.0.0)
